discal/__init__.py
discal/__main__.py
discord_cal-0.1.0.dist-info/entry_points.txt
discord_cal-0.1.0.dist-info/LICENSE
discord_cal-0.1.0.dist-info/WHEEL
discord_cal-0.1.0.dist-info/METADATA
discord_cal-0.1.0.dist-info/RECORD
